README.md
setup.cfg
setup.py
pycflare/__init__.py
pycflare/account.py
pycflare/kv.py
pycflare.egg-info/PKG-INFO
pycflare.egg-info/SOURCES.txt
pycflare.egg-info/dependency_links.txt
pycflare.egg-info/requires.txt
pycflare.egg-info/top_level.txt