Metadata-Version: 1.0
Name: pycflare
Version: 0.5
Summary: Python bindings for CloudFlare
Home-page: https://github.com/BillSchumacher/pycflare.git
Author: Bill Schumacher
Author-email: williamschumacher@gmail.com
License: BSD 0-Clause
Keywords: cloudflare workers kv
Platform: UNKNOWN
